colourize/__init__.py
colourize/_select.py
colourize/cli.py
colourize/colourize.py
colourize/colourspace.py
colourize/datasets.py
colourize/normalize.py
colourize/serialize.py
colourize/transforms.py
colourize-0.1.0.dist-info/entry_points.txt
colourize-0.1.0.dist-info/WHEEL
colourize-0.1.0.dist-info/METADATA
colourize-0.1.0.dist-info/RECORD
